zope.app.preference-4.1.0-py3.9-nspkg.pth
zope/app/preference/README.rst
zope/app/preference/__init__.py
zope/app/preference/browser.py
zope/app/preference/configure.zcml
zope/app/preference/default.py
zope/app/preference/ftesting.zcml
zope/app/preference/index.pt
zope/app/preference/interfaces.py
zope/app/preference/macros.pt
zope/app/preference/menu.pt
zope/app/preference/meta.zcml
zope/app/preference/metaconfigure.py
zope/app/preference/metadirectives.py
zope/app/preference/preference.py
zope/app/preference/subgroup.pt
zope/app/preference/testing.py
zope/app/preference/tests.py
zope.app.preference-4.1.0.dist-info/LICENSE.txt
zope.app.preference-4.1.0.dist-info/METADATA
zope.app.preference-4.1.0.dist-info/WHEEL
zope.app.preference-4.1.0.dist-info/namespace_packages.txt
zope.app.preference-4.1.0.dist-info/top_level.txt
zope.app.preference-4.1.0.dist-info/RECORD
