Metadata-Version: 2.1
Name: zope.app.preference
Version: 4.1.0
Summary: User Preferences Framework ZMI UI
Home-page: http://github.com/zopefoundation/zope.app.preference
Author: Zope Foundation and Contributors
Author-email: zope-dev@zope.org
License: ZPL 2.1
Keywords: zope3 user preference
Platform: UNKNOWN
Classifier: Development Status :: 5 - Production/Stable
Classifier: Environment :: Web Environment
Classifier: Intended Audience :: Developers
Classifier: License :: OSI Approved :: Zope Public License
Classifier: Programming Language :: Python
Classifier: Programming Language :: Python :: 2
Classifier: Programming Language :: Python :: 2.7
Classifier: Programming Language :: Python :: 3
Classifier: Programming Language :: Python :: 3.5
Classifier: Programming Language :: Python :: 3.6
Classifier: Programming Language :: Python :: 3.7
Classifier: Programming Language :: Python :: 3.8
Classifier: Programming Language :: Python :: 3.9
Classifier: Programming Language :: Python :: 3.10
Classifier: Programming Language :: Python :: Implementation :: CPython
Classifier: Programming Language :: Python :: Implementation :: PyPy
Classifier: Natural Language :: English
Classifier: Operating System :: OS Independent
Classifier: Topic :: Internet :: WWW/HTTP
Classifier: Framework :: Zope :: 3
License-File: LICENSE.txt
Requires-Dist: setuptools
Requires-Dist: zope.app.form (>=5.0.0)
Requires-Dist: zope.app.tree (>=4.0.0)
Requires-Dist: zope.preference
Provides-Extra: test
Requires-Dist: docutils ; extra == 'test'
Requires-Dist: webtest ; extra == 'test'
Requires-Dist: zope.app.basicskin (>=4.0.0) ; extra == 'test'
Requires-Dist: zope.app.rotterdam (>=4.0.0) ; extra == 'test'
Requires-Dist: zope.app.security (>=4.0.0) ; extra == 'test'
Requires-Dist: zope.app.wsgi (>=4.1.0) ; extra == 'test'
Requires-Dist: zope.principalannotation ; extra == 'test'
Requires-Dist: zope.principalregistry ; extra == 'test'
Requires-Dist: zope.testbrowser (>=5.2) ; extra == 'test'
Requires-Dist: zope.testing ; extra == 'test'
Requires-Dist: zope.testrunner ; extra == 'test'
